TestMath_rjkhan/__init__.py
TestMath_rjkhan/example.py
TestMath_rjkhan-0.0.6.dist-info/METADATA
TestMath_rjkhan-0.0.6.dist-info/WHEEL
TestMath_rjkhan-0.0.6.dist-info/top_level.txt
TestMath_rjkhan-0.0.6.dist-info/RECORD
