Metadata-Version: 2.1
Name: TestMath-rjkhan
Version: 0.0.6
Summary: Arithmatic Operations
Home-page: UNKNOWN
Author: Rabnawaz
Author-email: rabnawazjansher8@gmail.com
License: UNKNOWN
Keywords: python,first package
Platform: UNKNOWN
Classifier: Development Status :: 3 - Alpha
Classifier: Intended Audience :: Education
Classifier: Programming Language :: Python :: 2
Classifier: Programming Language :: Python :: 3
Classifier: Operating System :: MacOS :: MacOS X
Classifier: Operating System :: Microsoft :: Windows
